sectorizedradialprofile/__init__.py
sectorizedradialprofile/calculate_radial_profile.py
sectorizedradialprofile-1.1.2.dist-info/METADATA
sectorizedradialprofile-1.1.2.dist-info/WHEEL
sectorizedradialprofile-1.1.2.dist-info/top_level.txt
sectorizedradialprofile-1.1.2.dist-info/RECORD
