Metadata-Version: 2.1
Name: sectorizedradialprofile
Version: 1.1.2
Summary: Radial profile of a given sector of an 2D array
Home-page: https://github.com/JeanBilheux/SectorizedRadialProfile
Author: Jean Bilheux
Author-email: bilheuxjm@ornl.gov
License: BSD
Keywords: tiff tif profile radial sector
Platform: UNKNOWN
Classifier: Development Status :: 3 - Alpha
Classifier: Topic :: Scientific/Engineering :: Physics
Classifier: Intended Audience :: Developers
Classifier: Programming Language :: Python :: 3.6
Classifier: Programming Language :: Python :: 3.7
Requires-Dist: numpy
Requires-Dist: pandas
Requires-Dist: scikit-image
